odoo8_addon_stock_reserve_sale-8.0.1.0.1.99.dev39-py3.8-nspkg.pth
odoo_addons/stock_reserve_sale/README.rst
odoo_addons/stock_reserve_sale/__init__.py
odoo_addons/stock_reserve_sale/__openerp__.py
odoo_addons/stock_reserve_sale/i18n/am.po
odoo_addons/stock_reserve_sale/i18n/ar.po
odoo_addons/stock_reserve_sale/i18n/bg.po
odoo_addons/stock_reserve_sale/i18n/bs.po
odoo_addons/stock_reserve_sale/i18n/ca.po
odoo_addons/stock_reserve_sale/i18n/ca_ES.po
odoo_addons/stock_reserve_sale/i18n/cs.po
odoo_addons/stock_reserve_sale/i18n/da.po
odoo_addons/stock_reserve_sale/i18n/de.po
odoo_addons/stock_reserve_sale/i18n/el_GR.po
odoo_addons/stock_reserve_sale/i18n/en_AU.po
odoo_addons/stock_reserve_sale/i18n/en_GB.po
odoo_addons/stock_reserve_sale/i18n/es.po
odoo_addons/stock_reserve_sale/i18n/es_AR.po
odoo_addons/stock_reserve_sale/i18n/es_CL.po
odoo_addons/stock_reserve_sale/i18n/es_CO.po
odoo_addons/stock_reserve_sale/i18n/es_CR.po
odoo_addons/stock_reserve_sale/i18n/es_DO.po
odoo_addons/stock_reserve_sale/i18n/es_EC.po
odoo_addons/stock_reserve_sale/i18n/es_ES.po
odoo_addons/stock_reserve_sale/i18n/es_MX.po
odoo_addons/stock_reserve_sale/i18n/es_PE.po
odoo_addons/stock_reserve_sale/i18n/es_PY.po
odoo_addons/stock_reserve_sale/i18n/es_VE.po
odoo_addons/stock_reserve_sale/i18n/et.po
odoo_addons/stock_reserve_sale/i18n/fa.po
odoo_addons/stock_reserve_sale/i18n/fi.po
odoo_addons/stock_reserve_sale/i18n/fr.po
odoo_addons/stock_reserve_sale/i18n/fr_CA.po
odoo_addons/stock_reserve_sale/i18n/fr_CH.po
odoo_addons/stock_reserve_sale/i18n/fr_FR.po
odoo_addons/stock_reserve_sale/i18n/gl.po
odoo_addons/stock_reserve_sale/i18n/gl_ES.po
odoo_addons/stock_reserve_sale/i18n/he.po
odoo_addons/stock_reserve_sale/i18n/hi.po
odoo_addons/stock_reserve_sale/i18n/hr.po
odoo_addons/stock_reserve_sale/i18n/hr_HR.po
odoo_addons/stock_reserve_sale/i18n/hu.po
odoo_addons/stock_reserve_sale/i18n/id.po
odoo_addons/stock_reserve_sale/i18n/it.po
odoo_addons/stock_reserve_sale/i18n/ja.po
odoo8_addon_stock_reserve_sale-8.0.1.0.1.99.dev39.dist-info/METADATA
odoo8_addon_stock_reserve_sale-8.0.1.0.1.99.dev39.dist-info/WHEEL
odoo8_addon_stock_reserve_sale-8.0.1.0.1.99.dev39.dist-info/namespace_packages.txt
odoo8_addon_stock_reserve_sale-8.0.1.0.1.99.dev39.dist-info/top_level.txt
odoo8_addon_stock_reserve_sale-8.0.1.0.1.99.dev39.dist-info/RECORD
